{
    "totalSolvedProblems": 167,
    "totalProblems": 3977,
    "solvedEasyProblems": 64,
    "totalEasyProblems": 951,
    "easyBackgroundColor": "#1cbaba",
    "easyTextColor": "#1cbaba",
    "solvedMediumProblems": 86,
    "totalMediumProblems": 2077,
    "mediumBackgroundColor": "#ffb700",
    "mediumTextColor": "#ffb700",
    "solvedHardProblems": 17,
    "totalHardProblems": 949,
    "hardBackgroundColor": "#f63737",
    "hardTextColor": "#f63737",
    "primaryTextColor": "#ffffff",
    "secondaryTextColor": "#767676",
    "fontfamily": "Inter, Arial, Helvetica, sans-serif",
    "totalCardWidth": 608,
    "totalCardHeight": 220,
    "totalCardPrimaryTextFontSize": 70,
    "totalCardSecondaryTextFontSize": 25,
    "totalCardBackgroundColor": "#282828",
    "totalCardPadding": 16,
    "totalCardBorderRadius": 8,
    "totalCardEachBarBorderRadius": 4,
    "sectionCardWidth": 200,
    "sectionCardHeight": 120,
    "sectionTitleTextFontSize": 18,
    "sectionCardPrimaryTextFontSize": 35,
    "sectionCardSecondaryTextFontSize": 25
}